nonebot_plugin_sticker_saver/__init__.py
nonebot_plugin_sticker_saver-0.1.4.dist-info/LICENSE
nonebot_plugin_sticker_saver-0.1.4.dist-info/METADATA
nonebot_plugin_sticker_saver-0.1.4.dist-info/WHEEL
nonebot_plugin_sticker_saver-0.1.4.dist-info/RECORD
