Metadata-Version: 2.3
Name: nonebot-plugin-sticker-saver
Version: 0.1.4
Summary: A very simple Nonebot plugin for saving QQ emoticons that no longer have a save option.
License: MIT
Keywords: nonebot2,表情包,sticker
Author: Colanns
Author-email: mycolands@gmail.com
Requires-Python: >=3.8,<4.0
Classifier: License :: OSI Approved :: MIT License
Classifier: Programming Language :: Python :: 3
Classifier: Programming Language :: Python :: 3.8
Classifier: Programming Language :: Python :: 3.9
Classifier: Programming Language :: Python :: 3.10
Classifier: Programming Language :: Python :: 3.11
Classifier: Programming Language :: Python :: 3.12
Classifier: Programming Language :: Python :: 3.13
Requires-Dist: httpx (>=0.20.0)
Requires-Dist: nonebot-adapter-onebot (>=2.0.0-beta.1,<3.0.0)
Requires-Dist: nonebot2 (>=2.0.0-beta.4,<3.0.0)
Project-URL: Documentation, https://github.com/colasama/nonebot-plugin-sticker-saver
Project-URL: Homepage, https://github.com/colasama/nonebot-plugin-sticker-saver
Project-URL: Repository, https://github.com/colasama/nonebot-plugin-sticker-saver
